.travis.yml
AUTHORS
CHANGELOG.md
CONTRIBUTING.md
ChangeLog
LICENSE
README.md
requirements.txt
setup.cfg
setup.py
sonar-project.properties
test-requirements.txt
test.md
tox.ini
.github/ISSUE_TEMPLATE/bug_report.md
.github/ISSUE_TEMPLATE/feature_request.md
docs/AbstractProjectDto.md
docs/AbstractProjectDtoV2.md
docs/AddCommentDto.md
docs/AddTargetLangDto.md
docs/AddWorkflowStepsDto.md
docs/AdminProjectManager.md
docs/AdminProjectManagerV2.md
docs/AnalyseDto.md
docs/AnalyseJobDto.md
docs/AnalyseJobReference.md
docs/AnalyseLanguagePartDto.md
docs/AnalyseLanguagePartV2Dto.md
docs/AnalyseSettingsDto.md
docs/AnalyseV2Dto.md
docs/AnalysisApi.md
docs/AnalyticsApi.md
docs/AnalyticsDto.md
docs/AnalyticsResponseDto.md
docs/AndroidSettingsDto.md
docs/AssignVendorDto.md
docs/AssignableTemplatesDto.md
docs/AssignedJobDto.md
docs/AssignmentPerTargetLangDto.md
docs/AsyncAnalyseListResponseDto.md
docs/AsyncAnalyseResponseDto.md
docs/AsyncExportTMDto.md
docs/AsyncExportTMResponseDto.md
docs/AsyncRequestApi.md
docs/AsyncRequestDto.md
docs/AsyncRequestReference.md
docs/AsyncRequestWrapperDto.md
docs/AsyncResponseDto.md
docs/Attribute.md
docs/AuthSchema.md
docs/AuthenticationApi.md
docs/AutomatedProjectSettingsDto.md
docs/BackgroundTasksTbDto.md
docs/BackgroundTasksTmDto.md
docs/BilingualFileApi.md
docs/BrowseRequestDto.md
docs/BrowseResponseListDto.md
docs/BulkDeleteAnalyseDto.md
docs/BulkEditAnalyseDto.md
docs/BusinessUnitApi.md
docs/BusinessUnitDto.md
docs/BusinessUnitEditDto.md
docs/BusinessUnitReference.md
docs/Buyer.md
docs/BuyerReference.md
docs/CheckResponse.md
docs/ClientApi.md
docs/ClientDto.md
docs/ClientEditDto.md
docs/ClientReference.md
docs/CloneProjectDto.md
docs/Cloudy.png
docs/Cloudy_shell.png
docs/CommentDto.md
docs/CommonConversationDto.md
docs/ComparedSegmentDto.md
docs/ComparedSegmentsDto.md
docs/ConceptDto.md
docs/ConceptDtov2.md
docs/ConceptListReference.md
docs/ConnectorApi.md
docs/ConnectorDto.md
docs/ConnectorListDto.md
docs/ContinuousJobInfoDto.md
memsource_cli.egg-info/PKG-INFO
memsource_cli.egg-info/SOURCES.txt
memsource_cli.egg-info/dependency_links.txt
memsource_cli.egg-info/entry_points.txt
memsource_cli.egg-info/not-zip-safe
memsource_cli.egg-info/pbr.json
memsource_cli.egg-info/requires.txt
memsource_cli.egg-info/top_level.txt
