Metadata-Version: 2.1
Name: memsource-cli
Version: 0.3.7
Summary: Unofficial Memsource CLI client
Home-page: https://github.com/unofficial-memsource/memsource-cli-client/
Author: Robin Černín
Author-email: cerninr@gmail.com
License: UNKNOWN
Keywords: memsource
Platform: UNKNOWN
